exampleapp/__init__.py
exampleapp/defender.sb
exampleapp/readme.md
exampleapp/settings.py
exampleapp/urls.py
exampleapp/utils.py
gdmty_django_defender/__init__.py
gdmty_django_defender/admin.py
gdmty_django_defender/apps.py
gdmty_django_defender/ci_settings.py
gdmty_django_defender/config.py
gdmty_django_defender/connection.py
gdmty_django_defender/data.py
gdmty_django_defender/decorators.py
gdmty_django_defender/middleware.py
gdmty_django_defender/models.py
gdmty_django_defender/signals.py
gdmty_django_defender/tasks.py
gdmty_django_defender/test.py
gdmty_django_defender/test_settings.py
gdmty_django_defender/test_urls.py
gdmty_django_defender/tests.py
gdmty_django_defender/urls.py
gdmty_django_defender/utils.py
gdmty_django_defender/views.py
gdmty_django_defender/management/__init__.py
gdmty_django_defender/management/commands/__init__.py
gdmty_django_defender/management/commands/cleanup_django_defender.py
gdmty_django_defender/migrations/0001_initial.py
gdmty_django_defender/migrations/__init__.py
gdmty_django_defender/templates/admin/defender/app_index.html
gdmty_django_defender/templates/defender/lockout.html
gdmty_django_defender/templates/defender/admin/blocks.html
gdmty_django_defender-0.0.1.dist-info/LICENSE
gdmty_django_defender-0.0.1.dist-info/METADATA
gdmty_django_defender-0.0.1.dist-info/WHEEL
gdmty_django_defender-0.0.1.dist-info/top_level.txt
gdmty_django_defender-0.0.1.dist-info/RECORD
